{
  "project_info": {
    "project_number": "510233215110",
    "project_id": "hole-master-eat-them-all--pn",
    "storage_bucket": "hole-master-eat-them-all--pn.firebasestorage.app"
  },
  "client": [
    {
      "client_info": {
        "mobilesdk_app_id": "1:510233215110:android:2896b3fdfd2329a369d107",
        "android_client_info": {
          "package_name": "com.holemaster.eatthemall.holeiomaster"
        }
      },
      "oauth_client": [],
      "api_key": [
        {
          "current_key": "AIzaSyD0N8zCaDc4ZDjtaCv3bR1PJrbfiz5RsSM"
        }
      ],
      "services": {
        "appinvite_service": {
          "other_platform_oauth_client": []
        }
      }
    }
  ],
  "configuration_version": "1"
}